plain/htmx/CHANGELOG.md
plain/htmx/README.md
plain/htmx/__init__.py
plain/htmx/templates.py
plain/htmx/views.py
plain/htmx/assets/htmx/plainhtmx.js
plain/htmx/assets/htmx/vendor/idiomorph/idiomorph-ext.js
plain/htmx/assets/htmx/vendor/idiomorph/idiomorph-ext.min.js
plain/htmx/assets/htmx/vendor/idiomorph/idiomorph-htmx.js
plain/htmx/assets/htmx/vendor/idiomorph/idiomorph.amd.js
plain/htmx/assets/htmx/vendor/idiomorph/idiomorph.cjs.js
plain/htmx/assets/htmx/vendor/idiomorph/idiomorph.esm.js
plain/htmx/assets/htmx/vendor/idiomorph/idiomorph.js
plain/htmx/assets/htmx/vendor/idiomorph/idiomorph.min.js
plain/htmx/assets/htmx/vendor/src/htmx.amd.js
plain/htmx/assets/htmx/vendor/src/htmx.cjs.js
plain/htmx/assets/htmx/vendor/src/htmx.esm.d.ts
plain/htmx/assets/htmx/vendor/src/htmx.esm.js
plain/htmx/assets/htmx/vendor/src/htmx.js
plain/htmx/assets/htmx/vendor/src/htmx.min.js
plain/htmx/assets/htmx/vendor/src/htmx.min.js.gz
plain/htmx/assets/htmx/vendor/src/ext/README.md
plain/htmx/assets/htmx/vendor/src/ext/ajax-header.js
plain/htmx/assets/htmx/vendor/src/ext/alpine-morph.js
plain/htmx/assets/htmx/vendor/src/ext/class-tools.js
plain/htmx/assets/htmx/vendor/src/ext/client-side-templates.js
plain/htmx/assets/htmx/vendor/src/ext/debug.js
plain/htmx/assets/htmx/vendor/src/ext/disable-element.js
plain/htmx/assets/htmx/vendor/src/ext/event-header.js
plain/htmx/assets/htmx/vendor/src/ext/head-support.js
plain/htmx/assets/htmx/vendor/src/ext/include-vals.js
plain/htmx/assets/htmx/vendor/src/ext/json-enc.js
plain/htmx/assets/htmx/vendor/src/ext/loading-states.js
plain/htmx/assets/htmx/vendor/src/ext/method-override.js
plain/htmx/assets/htmx/vendor/src/ext/morphdom-swap.js
plain/htmx/assets/htmx/vendor/src/ext/multi-swap.js
plain/htmx/assets/htmx/vendor/src/ext/path-deps.js
plain/htmx/assets/htmx/vendor/src/ext/path-params.js
plain/htmx/assets/htmx/vendor/src/ext/preload.js
plain/htmx/assets/htmx/vendor/src/ext/rails-method.js
plain/htmx/assets/htmx/vendor/src/ext/remove-me.js
plain_htmx-0.15.1.dist-info/METADATA
plain_htmx-0.15.1.dist-info/WHEEL
plain_htmx-0.15.1.dist-info/licenses/LICENSE
plain_htmx-0.15.1.dist-info/RECORD
