Metadata-Version: 2.4
Name: plain.htmx
Version: 0.15.1
Summary: Integrate HTMX with templates and views.
Author-email: Dave Gaeddert <dave.gaeddert@dropseed.dev>
License-Expression: BSD-3-Clause
License-File: LICENSE
Requires-Python: >=3.13
Requires-Dist: plain<1.0.0
